 {"meta":{"description":"When making your sim, remember the KISS Principle: Keep It Simple, Sucka.\n\nAt the bottom of this sidebar, you can SAVE and SHARE your sim. Have fun! ðŸ˜˜","draw":2,"fps":29,"play":true},"states":[{"id":0,"icon":"","name":"empty spot","actions":[{"type":"if_random","probability":0.001,"actions":[{"type":"go_to_state","stateID":1,"actions":[]}]},{"probability":0.001,"actions":[{"stateID":"3","type":"go_to_state"}],"type":"if_random"}],"description":"Grows trees."},{"id":1,"icon":"ðŸ®","name":"cow","actions":[{"type":"if_random","probability":0.003,"actions":[{"type":"go_to_state","stateID":2,"actions":[]}]},{"type":"if_neighbor","sign":">=","num":1,"stateID":2,"actions":[{"type":"go_to_state","stateID":"4","actions":[]}]}],"description":"Catches on fire if hit by lightning, or if a neighbor's on fire."},{"id":2,"icon":"ðŸ”ª","name":"knife","actions":[{"probability":0.85,"actions":[{"stateID":0,"type":"go_to_state"}],"type":"if_random"}],"description":"Burns away."},{"id":3,"icon":"ðŸ·","name":"pig","description":"Click icon & paste in new emoji:\nMac: press control+command+space\nOther: copy from Emojipedia.org","actions":[{"probability":0.003,"actions":[{"stateID":"2","type":"go_to_state"}],"type":"if_random"},{"sign":">=","num":1,"stateID":"2","actions":[{"stateID":"5","type":"go_to_state"}],"type":"if_neighbor"}]},{"id":4,"icon":"ðŸ”","name":"hamburger","description":"Click icon & paste in new emoji:\nMac: press control+command+space\nOther: copy from Emojipedia.org","actions":[{"probability":0.01,"actions":[{"stateID":"6","type":"go_to_state"}],"type":"if_random"}]},{"id":5,"icon":"ðŸŒ­","name":"hotdog","description":"Click icon & paste in new emoji:\nMac: press control+command+space\nOther: copy from Emojipedia.org","actions":[{"probability":0.15,"actions":[{"stateID":"6","type":"go_to_state"}],"type":"if_random"}]},{"id":6,"icon":"ðŸš¶ðŸ½","name":"hungry person","description":"Click icon & paste in new emoji:\nMac: press control+command+space\nOther: copy from Emojipedia.org","actions":[{"sign":">=","num":1,"stateID":"4","actions":[{"space":0,"spotStateID":"4","leaveStateID":0,"type":"move_to"}],"type":"if_neighbor"},{"sign":">=","num":1,"stateID":"5","actions":[{"space":0,"spotStateID":"5","leaveStateID":0,"type":"move_to"}],"type":"if_neighbor"},{"probability":0.15,"actions":[{"stateID":0,"type":"go_to_state"}],"type":"if_random"}]}],"world":{"update":"simultaneous","neighborhood":"moore","proportions":[{"stateID":0,"parts":100},{"stateID":1,"parts":0},{"stateID":2,"parts":0},{"stateID":3,"parts":0},{"stateID":4,"parts":0},{"stateID":5,"parts":0},{"stateID":6,"parts":0}],"size":{"width":40,"height":33}}}